stix2viz/__init__.py
stix2viz/d3/LICENSE
stix2viz/d3/README.md
stix2viz/d3/d3.js
stix2viz/d3/d3.min.js
stix2viz/stix2viz/stix2viz.js
stix2viz/stix2viz/icons/stix2_attack_pattern_icon_tiny_round_v1.png
stix2viz/stix2viz/icons/stix2_autonomous_system_icon_tiny_round_v1.png
stix2viz/stix2viz/icons/stix2_bundle_icon_tiny_round_v1.png
stix2viz/stix2viz/icons/stix2_campaign_icon_tiny_round_v1.png
stix2viz/stix2viz/icons/stix2_coa_icon_tiny_round_v1.png
stix2viz/stix2viz/icons/stix2_course_of_action_icon_tiny_round_v1.png
stix2viz/stix2viz/icons/stix2_custom_object_icon_tiny_round_v1.svg
stix2viz/stix2viz/icons/stix2_domain_name_icon_tiny_round_v1.png
stix2viz/stix2viz/icons/stix2_email_addr_icon_tiny_round_v1.png
stix2viz/stix2viz/icons/stix2_email_message_icon_tiny_round_v1.png
stix2viz/stix2viz/icons/stix2_grouping_icon_tiny_round_v1.png
stix2viz/stix2viz/icons/stix2_http_icon_tiny_round_v1.png
stix2viz/stix2viz/icons/stix2_identity_icon_tiny_round_v1.png
stix2viz/stix2viz/icons/stix2_incident_icon_tiny_round_v1.png
stix2viz/stix2viz/icons/stix2_indicator_icon_tiny_round_v1.png
stix2viz/stix2viz/icons/stix2_infrastructure_icon_tiny_round_v1.png
stix2viz/stix2viz/icons/stix2_intrusion_set_icon_tiny_round_v1.png
stix2viz/stix2viz/icons/stix2_ipv4_addr_icon_tiny_round_v1.png
stix2viz/stix2viz/icons/stix2_ipv6_addr_icon_tiny_round_v1.png
stix2viz/stix2viz/icons/stix2_language_icon_tiny_round_v1.png
stix2viz/stix2viz/icons/stix2_location_icon_tiny_round_v1.png
stix2viz/stix2viz/icons/stix2_mac_addr_icon_tiny_round_v1.png
stix2viz/stix2viz/icons/stix2_malware_analysis_icon_tiny_round_v1.png
stix2viz/stix2viz/icons/stix2_malware_icon_tiny_round_v1.png
stix2viz/stix2viz/icons/stix2_marking_definition_icon_tiny_round_v1.png
stix2viz/stix2viz/icons/stix2_network_traffic_icon_tiny_round_v1.png
stix2viz/stix2viz/icons/stix2_note_icon_tiny_round_v1.png
stix2viz/stix2viz/icons/stix2_observed_data_icon_tiny_round_v1.png
stix2viz/stix2viz/icons/stix2_opinion_icon_tiny_round_v1.png
stix2_viz-0.3.0.dist-info/LICENSE
stix2_viz-0.3.0.dist-info/METADATA
stix2_viz-0.3.0.dist-info/WHEEL
stix2_viz-0.3.0.dist-info/top_level.txt
stix2_viz-0.3.0.dist-info/RECORD
