Metadata-Version: 2.1
Name: stix2-viz
Version: 0.3.0
Summary: Visualize STIX content
Home-page: https://oasis-open.github.io/cti-documentation/
Author: OASIS Cyber Threat Intelligence Technical Committee
Author-email: cti-users@lists.oasis-open.org
License: BSD
Platform: UNKNOWN
Requires-Dist: jupyter (>=1.0.0)
